projman.py
projmanager_cli-0.1.0.dist-info/METADATA
projmanager_cli-0.1.0.dist-info/WHEEL
projmanager_cli-0.1.0.dist-info/entry_points.txt
projmanager_cli-0.1.0.dist-info/top_level.txt
projmanager_cli-0.1.0.dist-info/RECORD
