Metadata-Version: 2.4
Name: projmanager-cli
Version: 0.1.0
Summary: All-in-one project manager CLI tool
Author-email: kkyian <kkyian@icloud.com>
Requires-Python: >=3.7
Requires-Dist: click
Requires-Dist: requests
